swarmauri_keyproviders_mirrored/MirroredKeyProvider.py
swarmauri_keyproviders_mirrored/__init__.py
swarmauri_keyproviders_mirrored-0.2.0.dev4.dist-info/LICENSE
swarmauri_keyproviders_mirrored-0.2.0.dev4.dist-info/METADATA
swarmauri_keyproviders_mirrored-0.2.0.dev4.dist-info/WHEEL
swarmauri_keyproviders_mirrored-0.2.0.dev4.dist-info/entry_points.txt
swarmauri_keyproviders_mirrored-0.2.0.dev4.dist-info/RECORD
